{
  "graph_stats": {
    "label": "Voynichese (count>=2)",
    "n_types": 2385,
    "n_edges": 16905,
    "avg_degree": 14.176100628930818,
    "isolated_fraction": 0.020964360587002098,
    "n_components": 67,
    "largest_component_size": 695,
    "largest_component_share": 0.2914046121593291,
    "top10_component_sizes": [
      695,
      546,
      456,
      260,
      124,
      83,
      72,
      31,
      22,
      18
    ],
    "size_geq_5_components": 13,
    "size_geq_10_components": 10,
    "avg_clustering_coef": 0.4982224119176095
  },
  "n_families_size_geq_3": 14,
  "families": [
    {
      "size": 546,
      "total_freq": 7320,
      "head_word": "chedy",
      "members_preview": [
        [
          "chedy",
          494
        ],
        [
          "aiin",
          442
        ],
        [
          "Shedy",
          422
        ],
        [
          "cheey",
          170
        ],
        [
          "cheol",
          162
        ],
        [
          "qoky",
          139
        ],
        [
          "Sheey",
          139
        ],
        [
          "otal",
          134
        ],
        [
          "otar",
          134
        ],
        [
          "okal",
          128
        ],
        [
          "okar",
          118
        ],
        [
          "dai!n",
          111
        ],
        [
          "Sheol",
          111
        ],
        [
          "dair",
          98
        ],
        [
          "cheor",
          95
        ]
      ],
      "slot_summary": {
        "modal_length": 4,
        "n_aligned": 546,
        "slots": [
          {
            "pos": 0,
            "alternants": [
              [
                "ch",
                1792
              ],
              [
                "o",
                1529
              ],
              [
                "Sh",
                1094
              ],
              [
                "a",
                591
              ],
              [
                "d",
                520
              ],
              [
                "q",
                338
              ],
              [
                "k",
                313
              ],
              [
                "y",
                307
              ],
              [
                "t",
                240
              ],
              [
                "l",
                201
              ],
              [
                "s",
                136
              ],
              [
                "cTh",
                66
              ],
              [
                "p",
                63
              ],
              [
                "r",
                48
              ],
              [
                "cKh",
                29
              ],
              [
                "e",
                22
              ],
              [
                "cPh",
                16
              ],
              [
                "f",
                13
              ],
              [
                "cFh",
                2
              ]
            ],
            "is_invariant": false
          },
          {
            "pos": 1,
            "alternants": [
              [
                "e",
                2565
              ],
              [
                "o",
                782
              ],
              [
                "k",
                763
              ],
              [
                "t",
                719
              ],
              [
                "a",
                650
              ],
              [
                "ch",
                517
              ],
              [
                "i",
                506
              ],
              [
                "l",
                201
              ],
              [
                "Sh",
                142
              ],
              [
                "d",
                136
              ],
              [
                "r",
                100
              ],
              [
                "cKh",
                82
              ],
              [
                "p",
                66
              ],
              [
                "cTh",
                42
              ],
              [
                "s",
                12
              ],
              [
                "y",
                12
              ],
              [
                "f",
                12
              ],
              [
                "cPh",
                10
              ],
              [
                "cFh",
                3
              ]
            ],
            "is_invariant": false
          },
          {
            "pos": 2,
            "alternants": [
              [
                "d",
                1398
              ],
              [
                "o",
                1337
              ],
              [
                "a",
                1234
              ],
              [
                "e",
                1082
              ],
              [
                "i",
                1063
              ],
              [
                "k",
                337
              ],
              [
                "ch",
                209
              ],
              [
                "t",
                172
              ],
              [
                "cKh",
                127
              ],
              [
                "l",
                100
              ],
              [
                "cTh",
                82
              ],
              [
                "r",
                71
              ],
              [
                "Sh",
                44
              ],
              [
                "h",
                26
              ],
              [
                "p",
                11
              ],
              [
                "cPh",
                10
              ],
              [
                "y",
                6
              ],
              [
                "s",
                4
              ],
              [
                "m",
                3
              ],
              [
                "n",
                2
              ],
              [
                "cFh",
                2
              ]
            ],
            "is_invariant": false
          },
          {
            "pos": 3,
            "alternants": [
              [
                "y",
                3362
              ],
              [
                "r",
                1255
              ],
              [
                "l",
                1193
              ],
              [
                "n",
                871
              ],
              [
                "m",
                193
              ],
              [
                "o",
                184
              ],
              [
                "s",
                176
              ],
              [
                "d",
                72
              ],
              [
                "k",
                5
              ],
              [
                "t",
                3
              ],
              [
                "i",
                2
              ],
              [
                "g",
                2
              ],
              [
                "f",
                2
              ]
            ],
            "is_invariant": false
          }
        ],
        "members_top": [
          [
            "chedy",
            494
          ],
          [
            "aiin",
            442
          ],
          [
            "Shedy",
            422
          ],
          [
            "cheey",
            170
          ],
          [
            "cheol",
            162
          ],
          [
            "qoky",
            139
          ],
          [
            "Sheey",
            139
          ],
          [
            "otal",
            134
          ],
          [
            "otar",
            134
          ],
          [
            "okal",
            128
          ],
          [
            "okar",
            118
          ],
          [
            "dai!n",
            111
          ]
        ]
      }
    },
    {
      "size": 695,
      "total_freq": 7026,
      "head_word": "daiin",
      "members_preview": [
        [
          "daiin",
          787
        ],
        [
          "qokal",
          184
        ],
        [
          "okeey",
          170
        ],
        [
          "otedy",
          153
        ],
        [
          "qokar",
          144
        ],
        [
          "oteey",
          134
        ],
        [
          "saiin",
          115
        ],
        [
          "okedy",
          114
        ],
        [
          "lchedy",
          108
        ],
        [
          "qokey",
          104
        ],
        [
          "qokol",
          101
        ],
        [
          "okai!n",
          99
        ],
        [
          "cheody",
          86
        ],
        [
          "Sheedy",
          83
        ],
        [
          "otai!n",
          75
        ]
      ],
      "slot_summary": {
        "modal_length": 5,
        "n_aligned": 695,
        "slots": [
          {
            "pos": 0,
            "alternants": [
              [
                "o",
                1894
              ],
              [
                "q",
                1214
              ],
              [
                "d",
                1050
              ],
              [
                "ch",
                739
              ],
              [
                "y",
                407
              ],
              [
                "l",
                374
              ],
              [
                "Sh",
                343
              ],
              [
                "k",
                258
              ],
              [
                "s",
                200
              ],
              [
                "t",
                168
              ],
              [
                "r",
                106
              ],
              [
                "a",
                106
              ],
              [
                "p",
                102
              ],
              [
                "cTh",
                16
              ],
              [
                "f",
                16
              ],
              [
                "cPh",
                11
              ],
              [
                "e",
                8
              ],
              [
                "c",
                7
              ],
              [
                "cKh",
                7
              ]
            ],
            "is_invariant": false
          },
          {
            "pos": 1,
            "alternants": [
              [
                "o",
                1581
              ],
              [
                "a",
                1382
              ],
              [
                "k",
                1105
              ],
              [
                "e",
                883
              ],
              [
                "t",
                855
              ],
              [
                "ch",
                496
              ],
              [
                "l",
                197
              ],
              [
                "Sh",
                179
              ],
              [
                "p",
                102
              ],
              [
                "i",
                60
              ],
              [
                "r",
                55
              ],
              [
                "d",
                52
              ],
              [
                "cKh",
                27
              ],
              [
                "cTh",
                17
              ],
              [
                "f",
                16
              ],
              [
                "y",
                9
              ],
              [
                "s",
                7
              ],
              [
                "cPh",
                3
              ]
            ],
            "is_invariant": false
          },
          {
            "pos": 2,
            "alternants": [
              [
                "e",
                2272
              ],
              [
                "i",
                1418
              ],
              [
                "k",
                932
              ],
              [
                "a",
                567
              ],
              [
                "ch",
                457
              ],
              [
                "t",
                420
              ],
              [
                "o",
                371
              ],
              [
                "d",
                207
              ],
              [
                "l",
                126
              ],
              [
                "r",
                65
              ],
              [
                "cKh",
                58
              ],
              [
                "p",
                47
              ],
              [
                "Sh",
                45
              ],
              [
                "cTh",
                15
              ],
              [
                "y",
                6
              ],
              [
                "s",
                6
              ],
              [
                "cPh",
                4
              ],
              [
                "f",
                4
              ],
              [
                "c",
                4
              ],
              [
                "h",
                2
              ]
            ],
            "is_invariant": false
          },
          {
            "pos": 3,
            "alternants": [
              [
                "i",
                1886
              ],
              [
                "d",
                1460
              ],
              [
                "e",
                1210
              ],
              [
                "a",
                993
              ],
              [
                "o",
                912
              ],
              [
                "ch",
                277
              ],
              [
                "l",
                100
              ],
              [
                "k",
                69
              ],
              [
                "r",
                39
              ],
              [
                "Sh",
                23
              ],
              [
                "cKh",
                17
              ],
              [
                "t",
                17
              ],
              [
                "cTh",
                11
              ],
              [
                "n",
                6
              ],
              [
                "s",
                4
              ],
              [
                "cPh",
                2
              ]
            ],
            "is_invariant": false
          },
          {
            "pos": 4,
            "alternants": [
              [
                "y",
                3023
              ],
              [
                "n",
                1763
              ],
              [
                "l",
                925
              ],
              [
                "r",
                844
              ],
              [
                "s",
                144
              ],
              [
                "m",
                144
              ],
              [
                "o",
                108
              ],
              [
                "d",
                75
              ]
            ],
            "is_invariant": false
          }
        ],
        "members_top": [
          [
            "daiin",
            787
          ],
          [
            "qokal",
            184
          ],
          [
            "okeey",
            170
          ],
          [
            "otedy",
            153
          ],
          [
            "qokar",
            144
          ],
          [
            "oteey",
            134
          ],
          [
            "saiin",
            115
          ],
          [
            "okedy",
            114
          ],
          [
            "lchedy",
            108
          ],
          [
            "qokey",
            104
          ],
          [
            "qokol",
            101
          ],
          [
            "okai!n",
            99
          ]
        ]
      }
    },
    {
      "size": 260,
      "total_freq": 5671,
      "head_word": "chol",
      "members_preview": [
        [
          "chol",
          373
        ],
        [
          "chey",
          331
        ],
        [
          "dar",
          292
        ],
        [
          "Shey",
          269
        ],
        [
          "dal",
          239
        ],
        [
          "chor",
          202
        ],
        [
          "Shol",
          172
        ],
        [
          "qol",
          146
        ],
        [
          "chdy",
          139
        ],
        [
          "chcKhy",
          127
        ],
        [
          "dol",
          110
        ],
        [
          "oty",
          110
        ],
        [
          "Shor",
          90
        ],
        [
          "oky",
          87
        ],
        [
          "dam",
          86
        ]
      ],
      "slot_summary": {
        "modal_length": 3,
        "n_aligned": 260,
        "slots": [
          {
            "pos": 0,
            "alternants": [
              [
                "ch",
                1658
              ],
              [
                "Sh",
                872
              ],
              [
                "d",
                870
              ],
              [
                "o",
                416
              ],
              [
                "s",
                277
              ],
              [
                "a",
                235
              ],
              [
                "k",
                219
              ],
              [
                "q",
                204
              ],
              [
                "t",
                195
              ],
              [
                "cTh",
                188
              ],
              [
                "l",
                184
              ],
              [
                "r",
                90
              ],
              [
                "cKh",
                82
              ],
              [
                "y",
                66
              ],
              [
                "p",
                42
              ],
              [
                "cPh",
                35
              ],
              [
                "e",
                16
              ],
              [
                "cFh",
                8
              ],
              [
                "f",
                6
              ],
              [
                "c",
                4
              ],
              [
                "x",
                2
              ],
              [
                "i",
                2
              ]
            ],
            "is_invariant": false
          },
          {
            "pos": 1,
            "alternants": [
              [
                "o",
                1935
              ],
              [
                "a",
                1278
              ],
              [
                "e",
                963
              ],
              [
                "d",
                260
              ],
              [
                "cKh",
                200
              ],
              [
                "t",
                180
              ],
              [
                "i",
                174
              ],
              [
                "k",
                171
              ],
              [
                "ch",
                137
              ],
              [
                "l",
                120
              ],
              [
                "cTh",
                117
              ],
              [
                "Sh",
                51
              ],
              [
                "r",
                47
              ],
              [
                "cPh",
                15
              ],
              [
                "h",
                8
              ],
              [
                "p",
                7
              ],
              [
                "f",
                2
              ],
              [
                "cFh",
                2
              ],
              [
                "s",
                2
              ],
              [
                "y",
                2
              ]
            ],
            "is_invariant": false
          },
          {
            "pos": 2,
            "alternants": [
              [
                "y",
                1899
              ],
              [
                "l",
                1596
              ],
              [
                "r",
                1337
              ],
              [
                "o",
                209
              ],
              [
                "m",
                205
              ],
              [
                "s",
                152
              ],
              [
                "n",
                123
              ],
              [
                "d",
                74
              ],
              [
                "k",
                31
              ],
              [
                "e",
                15
              ],
              [
                "t",
                13
              ],
              [
                "p",
                8
              ],
              [
                "g",
                7
              ],
              [
                "ch",
                2
              ]
            ],
            "is_invariant": false
          }
        ],
        "members_top": [
          [
            "chol",
            373
          ],
          [
            "chey",
            331
          ],
          [
            "dar",
            292
          ],
          [
            "Shey",
            269
          ],
          [
            "dal",
            239
          ],
          [
            "chor",
            202
          ],
          [
            "Shol",
            172
          ],
          [
            "qol",
            146
          ],
          [
            "chdy",
            139
          ],
          [
            "chcKhy",
            127
          ],
          [
            "dol",
            110
          ],
          [
            "oty",
            110
          ]
        ]
      }
    },
    {
      "size": 456,
      "total_freq": 4177,
      "head_word": "qokeey",
      "members_preview": [
        [
          "qokeey",
          305
        ],
        [
          "qokedy",
          263
        ],
        [
          "okaiin",
          201
        ],
        [
          "qokai!n",
          200
        ],
        [
          "otaiin",
          148
        ],
        [
          "okeedy",
          103
        ],
        [
          "oteedy",
          97
        ],
        [
          "qotedy",
          89
        ],
        [
          "qokain",
          72
        ],
        [
          "qokchdy",
          55
        ],
        [
          "qotai!n",
          54
        ],
        [
          "odaiin",
          52
        ],
        [
          "qokeol",
          49
        ],
        [
          "olaiin",
          48
        ],
        [
          "opchedy",
          48
        ]
      ],
      "slot_summary": {
        "modal_length": 6,
        "n_aligned": 456,
        "slots": [
          {
            "pos": 0,
            "alternants": [
              [
                "q",
                1665
              ],
              [
                "o",
                1474
              ],
              [
                "y",
                292
              ],
              [
                "ch",
                249
              ],
              [
                "l",
                181
              ],
              [
                "Sh",
                74
              ],
              [
                "d",
                63
              ],
              [
                "t",
                47
              ],
              [
                "k",
                45
              ],
              [
                "p",
                40
              ],
              [
                "a",
                22
              ],
              [
                "s",
                16
              ],
              [
                "f",
                4
              ],
              [
                "r",
                3
              ],
              [
                "e",
                2
              ]
            ],
            "is_invariant": false
          },
          {
            "pos": 1,
            "alternants": [
              [
                "o",
                1793
              ],
              [
                "k",
                822
              ],
              [
                "t",
                552
              ],
              [
                "l",
                314
              ],
              [
                "e",
                217
              ],
              [
                "ch",
                107
              ],
              [
                "d",
                104
              ],
              [
                "p",
                101
              ],
              [
                "r",
                53
              ],
              [
                "a",
                41
              ],
              [
                "Sh",
                41
              ],
              [
                "f",
                13
              ],
              [
                "s",
                10
              ],
              [
                "y",
                6
              ],
              [
                "cKh",
                3
              ]
            ],
            "is_invariant": false
          },
          {
            "pos": 2,
            "alternants": [
              [
                "k",
                1382
              ],
              [
                "e",
                876
              ],
              [
                "a",
                843
              ],
              [
                "t",
                385
              ],
              [
                "ch",
                298
              ],
              [
                "o",
                111
              ],
              [
                "d",
                74
              ],
              [
                "Sh",
                53
              ],
              [
                "l",
                41
              ],
              [
                "p",
                40
              ],
              [
                "i",
                36
              ],
              [
                "cKh",
                15
              ],
              [
                "r",
                10
              ],
              [
                "f",
                9
              ],
              [
                "cTh",
                2
              ],
              [
                "s",
                2
              ]
            ],
            "is_invariant": false
          },
          {
            "pos": 3,
            "alternants": [
              [
                "e",
                1956
              ],
              [
                "i",
                881
              ],
              [
                "a",
                547
              ],
              [
                "ch",
                301
              ],
              [
                "o",
                243
              ],
              [
                "d",
                124
              ],
              [
                "l",
                51
              ],
              [
                "k",
                35
              ],
              [
                "Sh",
                25
              ],
              [
                "t",
                4
              ],
              [
                "r",
                4
              ],
              [
                "y",
                4
              ],
              [
                "cKh",
                2
              ]
            ],
            "is_invariant": false
          },
          {
            "pos": 4,
            "alternants": [
              [
                "d",
                1442
              ],
              [
                "i",
                1401
              ],
              [
                "e",
                745
              ],
              [
                "o",
                336
              ],
              [
                "a",
                158
              ],
              [
                "l",
                38
              ],
              [
                "ch",
                33
              ],
              [
                "k",
                9
              ],
              [
                "Sh",
                7
              ],
              [
                "r",
                4
              ],
              [
                "y",
                2
              ],
              [
                "s",
                2
              ]
            ],
            "is_invariant": false
          },
          {
            "pos": 5,
            "alternants": [
              [
                "y",
                2188
              ],
              [
                "n",
                1339
              ],
              [
                "r",
                257
              ],
              [
                "l",
                244
              ],
              [
                "s",
                58
              ],
              [
                "o",
                37
              ],
              [
                "d",
                33
              ],
              [
                "m",
                19
              ],
              [
                "a",
                2
              ]
            ],
            "is_invariant": false
          }
        ],
        "members_top": [
          [
            "qokeey",
            305
          ],
          [
            "qokedy",
            263
          ],
          [
            "okaiin",
            201
          ],
          [
            "qokai!n",
            200
          ],
          [
            "otaiin",
            148
          ],
          [
            "okeedy",
            103
          ],
          [
            "oteedy",
            97
          ],
          [
            "qotedy",
            89
          ],
          [
            "qokain",
            72
          ],
          [
            "qokchdy",
            55
          ],
          [
            "qotai!n",
            54
          ],
          [
            "odaiin",
            52
          ]
        ]
      }
    },
    {
      "size": 72,
      "total_freq": 2729,
      "head_word": "ol",
      "members_preview": [
        [
          "ol",
          515
        ],
        [
          "or",
          336
        ],
        [
          "ar",
          334
        ],
        [
          "al",
          246
        ],
        [
          "dy",
          221
        ],
        [
          "chy",
          133
        ],
        [
          "Sho",
          117
        ],
        [
          "cThy",
          101
        ],
        [
          "Shy",
          90
        ],
        [
          "am",
          80
        ],
        [
          "cho",
          61
        ],
        [
          "cKhy",
          36
        ],
        [
          "qo",
          27
        ],
        [
          "os",
          27
        ],
        [
          "She",
          25
        ]
      ],
      "slot_summary": {
        "modal_length": 2,
        "n_aligned": 72,
        "slots": [
          {
            "pos": 0,
            "alternants": [
              [
                "o",
                923
              ],
              [
                "a",
                683
              ],
              [
                "d",
                261
              ],
              [
                "ch",
                256
              ],
              [
                "Sh",
                244
              ],
              [
                "cTh",
                115
              ],
              [
                "l",
                49
              ],
              [
                "cKh",
                39
              ],
              [
                "q",
                30
              ],
              [
                "s",
                28
              ],
              [
                "k",
                26
              ],
              [
                "r",
                23
              ],
              [
                "t",
                18
              ],
              [
                "cPh",
                16
              ],
              [
                "y",
                10
              ],
              [
                "cFh",
                5
              ],
              [
                "c",
                3
              ]
            ],
            "is_invariant": false
          },
          {
            "pos": 1,
            "alternants": [
              [
                "l",
                814
              ],
              [
                "r",
                701
              ],
              [
                "y",
                696
              ],
              [
                "o",
                265
              ],
              [
                "m",
                104
              ],
              [
                "s",
                63
              ],
              [
                "e",
                27
              ],
              [
                "d",
                22
              ],
              [
                "a",
                12
              ],
              [
                "t",
                9
              ],
              [
                "k",
                8
              ],
              [
                "n",
                6
              ],
              [
                "cTh",
                2
              ]
            ],
            "is_invariant": false
          }
        ],
        "members_top": [
          [
            "ol",
            515
          ],
          [
            "or",
            336
          ],
          [
            "ar",
            334
          ],
          [
            "al",
            246
          ],
          [
            "dy",
            221
          ],
          [
            "chy",
            133
          ],
          [
            "Sho",
            117
          ],
          [
            "cThy",
            101
          ],
          [
            "Shy",
            90
          ],
          [
            "am",
            80
          ],
          [
            "cho",
            61
          ],
          [
            "cKhy",
            36
          ]
        ]
      }
    },
    {
      "size": 124,
      "total_freq": 983,
      "head_word": "qokeedy",
      "members_preview": [
        [
          "qokeedy",
          299
        ],
        [
          "qoteedy",
          74
        ],
        [
          "olkeedy",
          40
        ],
        [
          "qokchedy",
          39
        ],
        [
          "qopchedy",
          32
        ],
        [
          "qokeody",
          31
        ],
        [
          "qokeeey",
          26
        ],
        [
          "qotchedy",
          23
        ],
        [
          "okeeody",
          14
        ],
        [
          "qoteody",
          12
        ],
        [
          "qokeeol",
          11
        ],
        [
          "ykeeody",
          11
        ],
        [
          "qokShedy",
          11
        ],
        [
          "oteeody",
          10
        ],
        [
          "qokeeor",
          10
        ]
      ],
      "slot_summary": {
        "modal_length": 7,
        "n_aligned": 124,
        "slots": [
          {
            "pos": 0,
            "alternants": [
              [
                "q",
                698
              ],
              [
                "o",
                175
              ],
              [
                "y",
                30
              ],
              [
                "ch",
                24
              ],
              [
                "d",
                15
              ],
              [
                "s",
                14
              ],
              [
                "l",
                12
              ],
              [
                "p",
                7
              ],
              [
                "a",
                4
              ],
              [
                "Sh",
                4
              ]
            ],
            "is_invariant": false
          },
          {
            "pos": 1,
            "alternants": [
              [
                "o",
                736
              ],
              [
                "l",
                85
              ],
              [
                "k",
                77
              ],
              [
                "t",
                47
              ],
              [
                "e",
                14
              ],
              [
                "a",
                8
              ],
              [
                "p",
                6
              ],
              [
                "ch",
                6
              ],
              [
                "Sh",
                2
              ],
              [
                "y",
                2
              ]
            ],
            "is_invariant": false
          },
          {
            "pos": 2,
            "alternants": [
              [
                "k",
                560
              ],
              [
                "t",
                150
              ],
              [
                "e",
                135
              ],
              [
                "l",
                44
              ],
              [
                "p",
                44
              ],
              [
                "ch",
                18
              ],
              [
                "f",
                15
              ],
              [
                "o",
                10
              ],
              [
                "d",
                3
              ],
              [
                "r",
                2
              ],
              [
                "a",
                2
              ]
            ],
            "is_invariant": false
          },
          {
            "pos": 3,
            "alternants": [
              [
                "e",
                721
              ],
              [
                "ch",
                175
              ],
              [
                "o",
                30
              ],
              [
                "Sh",
                25
              ],
              [
                "k",
                22
              ],
              [
                "a",
                8
              ],
              [
                "l",
                2
              ]
            ],
            "is_invariant": false
          },
          {
            "pos": 4,
            "alternants": [
              [
                "e",
                777
              ],
              [
                "o",
                134
              ],
              [
                "d",
                52
              ],
              [
                "l",
                15
              ],
              [
                "ch",
                3
              ],
              [
                "s",
                2
              ]
            ],
            "is_invariant": false
          },
          {
            "pos": 5,
            "alternants": [
              [
                "d",
                796
              ],
              [
                "e",
                70
              ],
              [
                "a",
                56
              ],
              [
                "o",
                44
              ],
              [
                "ch",
                11
              ],
              [
                "s",
                4
              ],
              [
                "l",
                2
              ]
            ],
            "is_invariant": false
          },
          {
            "pos": 6,
            "alternants": [
              [
                "y",
                878
              ],
              [
                "r",
                48
              ],
              [
                "l",
                39
              ],
              [
                "s",
                10
              ],
              [
                "d",
                4
              ],
              [
                "m",
                4
              ]
            ],
            "is_invariant": false
          }
        ],
        "members_top": [
          [
            "qokeedy",
            299
          ],
          [
            "qoteedy",
            74
          ],
          [
            "olkeedy",
            40
          ],
          [
            "qokchedy",
            39
          ],
          [
            "qopchedy",
            32
          ],
          [
            "qokeody",
            31
          ],
          [
            "qokeeey",
            26
          ],
          [
            "qotchedy",
            23
          ],
          [
            "okeeody",
            14
          ],
          [
            "qoteody",
            12
          ],
          [
            "qokeeol",
            11
          ],
          [
            "ykeeody",
            11
          ]
        ]
      }
    },
    {
      "size": 83,
      "total_freq": 740,
      "head_word": "qokaiin",
      "members_preview": [
        [
          "qokaiin",
          262
        ],
        [
          "qotaiin",
          75
        ],
        [
          "qodaiin",
          39
        ],
        [
          "chodaiin",
          37
        ],
        [
          "chedaiin",
          30
        ],
        [
          "olkaiin",
          29
        ],
        [
          "Shodaiin",
          20
        ],
        [
          "chokaiin",
          16
        ],
        [
          "Shedaiin",
          13
        ],
        [
          "chekaiin",
          8
        ],
        [
          "todaiin",
          8
        ],
        [
          "chotaiin",
          8
        ],
        [
          "polaiin",
          7
        ],
        [
          "soraiin",
          6
        ],
        [
          "oldaiin",
          6
        ]
      ],
      "slot_summary": {
        "modal_length": 7,
        "n_aligned": 83,
        "slots": [
          {
            "pos": 0,
            "alternants": [
              [
                "q",
                403
              ],
              [
                "ch",
                130
              ],
              [
                "o",
                76
              ],
              [
                "Sh",
                43
              ],
              [
                "p",
                22
              ],
              [
                "s",
                15
              ],
              [
                "t",
                13
              ],
              [
                "a",
                8
              ],
              [
                "d",
                7
              ],
              [
                "k",
                7
              ],
              [
                "r",
                7
              ],
              [
                "l",
                5
              ],
              [
                "y",
                4
              ]
            ],
            "is_invariant": false
          },
          {
            "pos": 1,
            "alternants": [
              [
                "o",
                546
              ],
              [
                "e",
                84
              ],
              [
                "l",
                49
              ],
              [
                "k",
                15
              ],
              [
                "a",
                12
              ],
              [
                "t",
                10
              ],
              [
                "ch",
                7
              ],
              [
                "r",
                5
              ],
              [
                "y",
                4
              ],
              [
                "p",
                3
              ],
              [
                "d",
                3
              ],
              [
                "q",
                2
              ]
            ],
            "is_invariant": false
          },
          {
            "pos": 2,
            "alternants": [
              [
                "k",
                346
              ],
              [
                "d",
                190
              ],
              [
                "t",
                91
              ],
              [
                "l",
                24
              ],
              [
                "o",
                22
              ],
              [
                "r",
                21
              ],
              [
                "e",
                17
              ],
              [
                "a",
                12
              ],
              [
                "s",
                8
              ],
              [
                "p",
                5
              ],
              [
                "ch",
                4
              ]
            ],
            "is_invariant": false
          },
          {
            "pos": 3,
            "alternants": [
              [
                "a",
                684
              ],
              [
                "d",
                20
              ],
              [
                "k",
                13
              ],
              [
                "i",
                10
              ],
              [
                "o",
                9
              ],
              [
                "r",
                2
              ],
              [
                "e",
                2
              ]
            ],
            "is_invariant": false
          },
          {
            "pos": 4,
            "alternants": [
              [
                "i",
                705
              ],
              [
                "a",
                35
              ]
            ],
            "is_invariant": false
          },
          {
            "pos": 5,
            "alternants": [
              [
                "i",
                740
              ]
            ],
            "is_invariant": true
          },
          {
            "pos": 6,
            "alternants": [
              [
                "n",
                735
              ],
              [
                "r",
                5
              ]
            ],
            "is_invariant": false
          }
        ],
        "members_top": [
          [
            "qokaiin",
            262
          ],
          [
            "qotaiin",
            75
          ],
          [
            "qodaiin",
            39
          ],
          [
            "chodaiin",
            37
          ],
          [
            "chedaiin",
            30
          ],
          [
            "olkaiin",
            29
          ],
          [
            "Shodaiin",
            20
          ],
          [
            "chokaiin",
            16
          ],
          [
            "Shedaiin",
            13
          ],
          [
            "chekaiin",
            8
          ],
          [
            "todaiin",
            8
          ],
          [
            "chotaiin",
            8
          ]
        ]
      }
    },
    {
      "size": 31,
      "total_freq": 85,
      "head_word": "cheodaiin",
      "members_preview": [
        [
          "cheodaiin",
          8
        ],
        [
          "pchedaiin",
          4
        ],
        [
          "pchodaiin",
          4
        ],
        [
          "Sheodaiin",
          4
        ],
        [
          "otodaiin",
          4
        ],
        [
          "okedaiin",
          3
        ],
        [
          "qokedai!n",
          3
        ],
        [
          "qoedaiin",
          3
        ],
        [
          "chol!kaiin",
          3
        ],
        [
          "cheo!daiin",
          3
        ],
        [
          "cheedaiin",
          3
        ],
        [
          "otedaiin",
          3
        ],
        [
          "ytodaiin",
          3
        ],
        [
          "tchodaiin",
          3
        ],
        [
          "pShodaiin",
          2
        ]
      ],
      "slot_summary": {
        "modal_length": 8,
        "n_aligned": 31,
        "slots": [
          {
            "pos": 0,
            "alternants": [
              [
                "ch",
                25
              ],
              [
                "o",
                16
              ],
              [
                "q",
                14
              ],
              [
                "p",
                10
              ],
              [
                "Sh",
                6
              ],
              [
                "t",
                5
              ],
              [
                "y",
                5
              ],
              [
                "k",
                2
              ],
              [
                "d",
                2
              ]
            ],
            "is_invariant": false
          },
          {
            "pos": 1,
            "alternants": [
              [
                "e",
                32
              ],
              [
                "o",
                19
              ],
              [
                "ch",
                15
              ],
              [
                "t",
                12
              ],
              [
                "k",
                5
              ],
              [
                "Sh",
                2
              ]
            ],
            "is_invariant": false
          },
          {
            "pos": 2,
            "alternants": [
              [
                "o",
                41
              ],
              [
                "e",
                26
              ],
              [
                "k",
                7
              ],
              [
                "d",
                4
              ],
              [
                "t",
                4
              ],
              [
                "l",
                3
              ]
            ],
            "is_invariant": false
          },
          {
            "pos": 3,
            "alternants": [
              [
                "d",
                57
              ],
              [
                "k",
                9
              ],
              [
                "e",
                7
              ],
              [
                "a",
                6
              ],
              [
                "ch",
                6
              ]
            ],
            "is_invariant": false
          },
          {
            "pos": 4,
            "alternants": [
              [
                "a",
                72
              ],
              [
                "d",
                7
              ],
              [
                "i",
                6
              ]
            ],
            "is_invariant": false
          },
          {
            "pos": 5,
            "alternants": [
              [
                "i",
                78
              ],
              [
                "a",
                7
              ]
            ],
            "is_invariant": false
          },
          {
            "pos": 6,
            "alternants": [
              [
                "i",
                85
              ]
            ],
            "is_invariant": true
          },
          {
            "pos": 7,
            "alternants": [
              [
                "n",
                85
              ]
            ],
            "is_invariant": true
          }
        ],
        "members_top": [
          [
            "cheodaiin",
            8
          ],
          [
            "pchedaiin",
            4
          ],
          [
            "pchodaiin",
            4
          ],
          [
            "Sheodaiin",
            4
          ],
          [
            "otodaiin",
            4
          ],
          [
            "okedaiin",
            3
          ],
          [
            "qokedai!n",
            3
          ],
          [
            "qoedaiin",
            3
          ],
          [
            "chol!kaiin",
            3
          ],
          [
            "cheo!daiin",
            3
          ],
          [
            "cheedaiin",
            3
          ],
          [
            "otedaiin",
            3
          ]
        ]
      }
    },
    {
      "size": 18,
      "total_freq": 70,
      "head_word": "qokeeody",
      "members_preview": [
        [
          "qokeeody",
          12
        ],
        [
          "olkeeody",
          7
        ],
        [
          "qoteeody",
          6
        ],
        [
          "qokeeedy",
          5
        ],
        [
          "qol!keedy",
          4
        ],
        [
          "qokechedy",
          4
        ],
        [
          "qotcheedy",
          4
        ],
        [
          "qolkeedy",
          3
        ],
        [
          "solkeedy",
          3
        ],
        [
          "qokcheody",
          3
        ],
        [
          "qoteeedy",
          3
        ],
        [
          "olkeeedy",
          3
        ],
        [
          "chol!keedy",
          3
        ],
        [
          "salkeedy",
          2
        ],
        [
          "qopcheody",
          2
        ]
      ],
      "slot_summary": {
        "modal_length": 8,
        "n_aligned": 18,
        "slots": [
          {
            "pos": 0,
            "alternants": [
              [
                "q",
                50
              ],
              [
                "o",
                10
              ],
              [
                "s",
                5
              ],
              [
                "ch",
                3
              ],
              [
                "Sh",
                2
              ]
            ],
            "is_invariant": false
          },
          {
            "pos": 1,
            "alternants": [
              [
                "o",
                58
              ],
              [
                "l",
                10
              ],
              [
                "a",
                2
              ]
            ],
            "is_invariant": false
          },
          {
            "pos": 2,
            "alternants": [
              [
                "k",
                36
              ],
              [
                "l",
                17
              ],
              [
                "t",
                13
              ],
              [
                "p",
                4
              ]
            ],
            "is_invariant": false
          },
          {
            "pos": 3,
            "alternants": [
              [
                "e",
                40
              ],
              [
                "k",
                17
              ],
              [
                "ch",
                13
              ]
            ],
            "is_invariant": false
          },
          {
            "pos": 4,
            "alternants": [
              [
                "e",
                66
              ],
              [
                "ch",
                4
              ]
            ],
            "is_invariant": false
          },
          {
            "pos": 5,
            "alternants": [
              [
                "e",
                40
              ],
              [
                "o",
                30
              ]
            ],
            "is_invariant": false
          },
          {
            "pos": 6,
            "alternants": [
              [
                "d",
                70
              ]
            ],
            "is_invariant": true
          },
          {
            "pos": 7,
            "alternants": [
              [
                "y",
                70
              ]
            ],
            "is_invariant": true
          }
        ],
        "members_top": [
          [
            "qokeeody",
            12
          ],
          [
            "olkeeody",
            7
          ],
          [
            "qoteeody",
            6
          ],
          [
            "qokeeedy",
            5
          ],
          [
            "qol!keedy",
            4
          ],
          [
            "qokechedy",
            4
          ],
          [
            "qotcheedy",
            4
          ],
          [
            "qolkeedy",
            3
          ],
          [
            "solkeedy",
            3
          ],
          [
            "qokcheody",
            3
          ],
          [
            "qoteeedy",
            3
          ],
          [
            "olkeeedy",
            3
          ]
        ]
      }
    },
    {
      "size": 22,
      "total_freq": 58,
      "head_word": "okalal",
      "members_preview": [
        [
          "okalal",
          6
        ],
        [
          "okaral",
          4
        ],
        [
          "otalor",
          4
        ],
        [
          "otarar",
          4
        ],
        [
          "okalar",
          3
        ],
        [
          "okalor",
          3
        ],
        [
          "okaram",
          3
        ],
        [
          "otaram",
          3
        ],
        [
          "otalal",
          2
        ],
        [
          "otalar",
          2
        ],
        [
          "okalam",
          2
        ],
        [
          "okal!ar",
          2
        ],
        [
          "okolar",
          2
        ],
        [
          "okarol",
          2
        ],
        [
          "okalol",
          2
        ]
      ],
      "slot_summary": {
        "modal_length": 6,
        "n_aligned": 22,
        "slots": [
          {
            "pos": 0,
            "alternants": [
              [
                "o",
                56
              ],
              [
                "k",
                2
              ]
            ],
            "is_invariant": false
          },
          {
            "pos": 1,
            "alternants": [
              [
                "k",
                29
              ],
              [
                "t",
                23
              ],
              [
                "p",
                4
              ],
              [
                "a",
                2
              ]
            ],
            "is_invariant": false
          },
          {
            "pos": 2,
            "alternants": [
              [
                "a",
                50
              ],
              [
                "o",
                6
              ],
              [
                "l",
                2
              ]
            ],
            "is_invariant": false
          },
          {
            "pos": 3,
            "alternants": [
              [
                "l",
                38
              ],
              [
                "r",
                18
              ],
              [
                "k",
                2
              ]
            ],
            "is_invariant": false
          },
          {
            "pos": 4,
            "alternants": [
              [
                "a",
                43
              ],
              [
                "o",
                15
              ]
            ],
            "is_invariant": false
          },
          {
            "pos": 5,
            "alternants": [
              [
                "r",
                24
              ],
              [
                "l",
                22
              ],
              [
                "m",
                12
              ]
            ],
            "is_invariant": false
          }
        ],
        "members_top": [
          [
            "okalal",
            6
          ],
          [
            "okaral",
            4
          ],
          [
            "otalor",
            4
          ],
          [
            "otarar",
            4
          ],
          [
            "okalar",
            3
          ],
          [
            "okalor",
            3
          ],
          [
            "okaram",
            3
          ],
          [
            "otaram",
            3
          ],
          [
            "otalal",
            2
          ],
          [
            "otalar",
            2
          ],
          [
            "okalam",
            2
          ],
          [
            "okal!ar",
            2
          ]
        ]
      }
    },
    {
      "size": 8,
      "total_freq": 23,
      "head_word": "oteodaiin",
      "members_preview": [
        [
          "oteodaiin",
          6
        ],
        [
          "qotedaiin",
          3
        ],
        [
          "qokeedai!n",
          3
        ],
        [
          "qokedaiin",
          3
        ],
        [
          "qotcheaiin",
          2
        ],
        [
          "qoeedaiin",
          2
        ],
        [
          "olkedaiin",
          2
        ],
        [
          "okeodaiin",
          2
        ]
      ],
      "slot_summary": {
        "modal_length": 9,
        "n_aligned": 8,
        "slots": [
          {
            "pos": 0,
            "alternants": [
              [
                "q",
                13
              ],
              [
                "o",
                10
              ]
            ],
            "is_invariant": false
          },
          {
            "pos": 1,
            "alternants": [
              [
                "o",
                13
              ],
              [
                "t",
                6
              ],
              [
                "l",
                2
              ],
              [
                "k",
                2
              ]
            ],
            "is_invariant": false
          },
          {
            "pos": 2,
            "alternants": [
              [
                "e",
                10
              ],
              [
                "k",
                8
              ],
              [
                "t",
                5
              ]
            ],
            "is_invariant": false
          },
          {
            "pos": 3,
            "alternants": [
              [
                "e",
                13
              ],
              [
                "o",
                8
              ],
              [
                "ch",
                2
              ]
            ],
            "is_invariant": false
          },
          {
            "pos": 4,
            "alternants": [
              [
                "d",
                18
              ],
              [
                "e",
                5
              ]
            ],
            "is_invariant": false
          },
          {
            "pos": 5,
            "alternants": [
              [
                "a",
                20
              ],
              [
                "d",
                3
              ]
            ],
            "is_invariant": false
          },
          {
            "pos": 6,
            "alternants": [
              [
                "i",
                20
              ],
              [
                "a",
                3
              ]
            ],
            "is_invariant": false
          },
          {
            "pos": 7,
            "alternants": [
              [
                "i",
                23
              ]
            ],
            "is_invariant": true
          },
          {
            "pos": 8,
            "alternants": [
              [
                "n",
                23
              ]
            ],
            "is_invariant": true
          }
        ],
        "members_top": [
          [
            "oteodaiin",
            6
          ],
          [
            "qotedaiin",
            3
          ],
          [
            "qokeedai!n",
            3
          ],
          [
            "qokedaiin",
            3
          ],
          [
            "qotcheaiin",
            2
          ],
          [
            "qoeedaiin",
            2
          ],
          [
            "olkedaiin",
            2
          ],
          [
            "okeodaiin",
            2
          ]
        ]
      }
    },
    {
      "size": 6,
      "total_freq": 17,
      "head_word": "qokeedar",
      "members_preview": [
        [
          "qokeedar",
          6
        ],
        [
          "qokeedal",
          3
        ],
        [
          "qoteedar",
          2
        ],
        [
          "qokeodal",
          2
        ],
        [
          "okeodaly",
          2
        ],
        [
          "qotchedar",
          2
        ]
      ],
      "slot_summary": {
        "modal_length": 8,
        "n_aligned": 6,
        "slots": [
          {
            "pos": 0,
            "alternants": [
              [
                "q",
                15
              ],
              [
                "o",
                2
              ]
            ],
            "is_invariant": false
          },
          {
            "pos": 1,
            "alternants": [
              [
                "o",
                15
              ],
              [
                "k",
                2
              ]
            ],
            "is_invariant": false
          },
          {
            "pos": 2,
            "alternants": [
              [
                "k",
                11
              ],
              [
                "t",
                4
              ],
              [
                "e",
                2
              ]
            ],
            "is_invariant": false
          },
          {
            "pos": 3,
            "alternants": [
              [
                "e",
                13
              ],
              [
                "o",
                2
              ],
              [
                "ch",
                2
              ]
            ],
            "is_invariant": false
          },
          {
            "pos": 4,
            "alternants": [
              [
                "e",
                13
              ],
              [
                "o",
                2
              ],
              [
                "d",
                2
              ]
            ],
            "is_invariant": false
          },
          {
            "pos": 5,
            "alternants": [
              [
                "d",
                15
              ],
              [
                "a",
                2
              ]
            ],
            "is_invariant": false
          },
          {
            "pos": 6,
            "alternants": [
              [
                "a",
                15
              ],
              [
                "l",
                2
              ]
            ],
            "is_invariant": false
          },
          {
            "pos": 7,
            "alternants": [
              [
                "r",
                10
              ],
              [
                "l",
                5
              ],
              [
                "y",
                2
              ]
            ],
            "is_invariant": false
          }
        ],
        "members_top": [
          [
            "qokeedar",
            6
          ],
          [
            "qokeedal",
            3
          ],
          [
            "qoteedar",
            2
          ],
          [
            "qokeodal",
            2
          ],
          [
            "okeodaly",
            2
          ],
          [
            "qotchedar",
            2
          ]
        ]
      }
    },
    {
      "size": 5,
      "total_freq": 12,
      "head_word": "dairal",
      "members_preview": [
        [
          "dairal",
          4
        ],
        [
          "dairol",
          2
        ],
        [
          "daraly",
          2
        ],
        [
          "dairar",
          2
        ],
        [
          "sairol",
          2
        ]
      ],
      "slot_summary": {
        "modal_length": 6,
        "n_aligned": 5,
        "slots": [
          {
            "pos": 0,
            "alternants": [
              [
                "d",
                10
              ],
              [
                "s",
                2
              ]
            ],
            "is_invariant": false
          },
          {
            "pos": 1,
            "alternants": [
              [
                "a",
                12
              ]
            ],
            "is_invariant": true
          },
          {
            "pos": 2,
            "alternants": [
              [
                "i",
                10
              ],
              [
                "r",
                2
              ]
            ],
            "is_invariant": false
          },
          {
            "pos": 3,
            "alternants": [
              [
                "r",
                10
              ],
              [
                "a",
                2
              ]
            ],
            "is_invariant": false
          },
          {
            "pos": 4,
            "alternants": [
              [
                "a",
                6
              ],
              [
                "o",
                4
              ],
              [
                "l",
                2
              ]
            ],
            "is_invariant": false
          },
          {
            "pos": 5,
            "alternants": [
              [
                "l",
                8
              ],
              [
                "y",
                2
              ],
              [
                "r",
                2
              ]
            ],
            "is_invariant": false
          }
        ],
        "members_top": [
          [
            "dairal",
            4
          ],
          [
            "dairol",
            2
          ],
          [
            "daraly",
            2
          ],
          [
            "dairar",
            2
          ],
          [
            "sairol",
            2
          ]
        ]
      }
    },
    {
      "size": 3,
      "total_freq": 8,
      "head_word": "aIThy",
      "members_preview": [
        [
          "aIThy",
          4
        ],
        [
          "oIThy",
          2
        ],
        [
          "oIKhy",
          2
        ]
      ],
      "slot_summary": {
        "modal_length": 5,
        "n_aligned": 3,
        "slots": [
          {
            "pos": 0,
            "alternants": [
              [
                "a",
                4
              ],
              [
                "o",
                4
              ]
            ],
            "is_invariant": false
          },
          {
            "pos": 1,
            "alternants": [
              [
                "I",
                8
              ]
            ],
            "is_invariant": true
          },
          {
            "pos": 2,
            "alternants": [
              [
                "T",
                6
              ],
              [
                "K",
                2
              ]
            ],
            "is_invariant": false
          },
          {
            "pos": 3,
            "alternants": [
              [
                "h",
                8
              ]
            ],
            "is_invariant": true
          },
          {
            "pos": 4,
            "alternants": [
              [
                "y",
                8
              ]
            ],
            "is_invariant": true
          }
        ],
        "members_top": [
          [
            "aIThy",
            4
          ],
          [
            "oIThy",
            2
          ],
          [
            "oIKhy",
            2
          ]
        ]
      }
    }
  ]
}